sekte/Dwrapper.py
sekte/__init__.py
sekte/__main__.py
sekte2pdf-0.0.4.dist-info/METADATA
sekte2pdf-0.0.4.dist-info/WHEEL
sekte2pdf-0.0.4.dist-info/top_level.txt
sekte2pdf-0.0.4.dist-info/RECORD
